{"_type":"export","__export_format":4,"__export_date":"2023-09-13T23:39:13.922Z","__export_source":"insomnia.desktop.app:v2023.5.8","resources":[{"_id":"req_fbb9cef283f64bf790c828461712e94b","parentId":"wrk_c69e80b4de4f46598d2edc67e3d8af56","modified":1694648281824,"created":1694648267814,"url":"http://localhost:3000/items","name":"Get Grocery List","description":"","method":"GET","body":{},"parameters":[],"headers":[{"name":"User-Agent","value":"insomnia/2023.5.8"}],"authentication":{},"metaSortKey":-1694648267814,"isPrivate":false,"settingStoreCookies":true,"settingSendCookies":true,"settingDisableRenderRequestBody":false,"settingEncodeUrl":true,"settingRebuildPath":true,"settingFollowRedirects":"global","_type":"request"},{"_id":"wrk_c69e80b4de4f46598d2edc67e3d8af56","parentId":null,"modified":1694648157575,"created":1694648157575,"name":"API","description":"","scope":"collection","_type":"workspace"},{"_id":"req_c3ed7059625f4ca1bf3ff23285093f0c","parentId":"wrk_c69e80b4de4f46598d2edc67e3d8af56","modified":1694648223282,"created":1694648160216,"url":"http://localhost:3000/items","name":"Create Item","description":"","method":"POST","body":{"mimeType":"application/json","text":"{\n\t\"name\": \"bananas\",\n\t\"price\": 2.75\n}"},"parameters":[],"headers":[{"name":"Content-Type","value":"application/json"},{"name":"User-Agent","value":"insomnia/2023.5.8"}],"authentication":{},"metaSortKey":-1694648160216,"isPrivate":false,"settingStoreCookies":true,"settingSendCookies":true,"settingDisableRenderRequestBody":false,"settingEncodeUrl":true,"settingRebuildPath":true,"settingFollowRedirects":"global","_type":"request"},{"_id":"env_63f8e9a426972dcffda55689a3e01a5f31fdd473","parentId":"wrk_c69e80b4de4f46598d2edc67e3d8af56","modified":1694648157582,"created":1694648157582,"name":"Base Environment","data":{},"dataPropertyOrder":null,"color":null,"isPrivate":false,"metaSortKey":1694648157582,"_type":"environment"},{"_id":"jar_63f8e9a426972dcffda55689a3e01a5f31fdd473","parentId":"wrk_c69e80b4de4f46598d2edc67e3d8af56","modified":1694648157584,"created":1694648157584,"name":"Default Jar","cookies":[],"_type":"cookie_jar"}]}